dash_simple_map/DashSimpleMap.py
dash_simple_map/__init__.py
dash_simple_map/_imports_.py
dash_simple_map/dash_simple_map.min.js
dash_simple_map/dash_simple_map.min.js.map
dash_simple_map/metadata.json
dash_simple_map/package-info.json
dash_simple_map-0.0.3.dist-info/LICENSE
dash_simple_map-0.0.3.dist-info/METADATA
dash_simple_map-0.0.3.dist-info/WHEEL
dash_simple_map-0.0.3.dist-info/top_level.txt
dash_simple_map-0.0.3.dist-info/RECORD
