Metadata-Version: 2.1
Name: dash-simple-map
Version: 0.0.3
Summary: Project Description
Home-page: UNKNOWN
Author: Francois Quellec <francois.quellec@gmail.com>
Author-email: UNKNOWN
License: MIT
Platform: UNKNOWN
Classifier: Framework :: Dash
